muncher/__init__.py
muncher-0.0.1.dist-info/LICENSE
muncher-0.0.1.dist-info/METADATA
muncher-0.0.1.dist-info/WHEEL
muncher-0.0.1.dist-info/top_level.txt
muncher-0.0.1.dist-info/RECORD
